MANIFEST.in
__info__.py
setup.py
./appomatic_photolog.egg-info/SOURCES.txt
./appomatic_photolog.egg-info/dependency_links.txt
./appomatic_photolog.egg-info/requires.txt
./appomatic_photolog.egg-info/top_level.txt
appomatic_photolog/__app__.py
appomatic_photolog/__init__.py
appomatic_photolog/__urls__.py
appomatic_photolog.egg-info/PKG-INFO
appomatic_photolog.egg-info/SOURCES.txt
appomatic_photolog.egg-info/dependency_links.txt
appomatic_photolog.egg-info/requires.txt
appomatic_photolog.egg-info/top_level.txt