Metadata-Version: 1.0
Name: appomatic-photolog
Version: 0.0.32
Summary: Photologue is a reusable Django application that provides powerful image management and manipulation functionality as well as a complete photo gallery solution.
Home-page: http://code.google.com/p/django-photologue/
Author: RedHog (Egil Moeller)
Author-email: egil.moller@freecode.no
License: GPL
Keywords: appomatic photologue
Platform: UNKNOWN
